scspecies/__init__.py
scspecies/models.py
scspecies/plot.py
scspecies/preprocessing.py
scspecies-0.1.4.dist-info/licenses/LICENSE.txt
scspecies-0.1.4.dist-info/METADATA
scspecies-0.1.4.dist-info/WHEEL
scspecies-0.1.4.dist-info/top_level.txt
scspecies-0.1.4.dist-info/RECORD
