Metadata-Version: 2.4
Name: scspecies
Version: 0.1.4
Summary: scspecies allows users to align latent representations of single-cell datasets from different species.
Author: Clemens Schächter
License: MIT
Project-URL: Homepage, https://scspecies.readthedocs.io/
Project-URL: Repository, https://github.com/cschaech/scspecies_package
Project-URL: Documentation, https://scspecies.readthedocs.io/
Keywords: single-cell,comparative analysis,cross-species,transfer learning,alignment,deep-learning,scspecies
Classifier: Development Status :: 4 - Beta
Classifier: Intended Audience :: Science/Research
Classifier: License :: OSI Approved :: MIT License
Classifier: Programming Language :: Python :: 3.11
Classifier: Topic :: Scientific/Engineering :: Bio-Informatics
Requires-Python: >=3.11
License-File: LICENSE.txt
Requires-Dist: torch<3.0.0,>=2.7.0
Requires-Dist: muon<0.2.0,>=0.1.7
Requires-Dist: scipy<2.0.0,>=1.15.3
Requires-Dist: tqdm<5.0.0,>=4.67.1
Requires-Dist: h5py<4.0.0,>=3.13.0
Requires-Dist: seaborn<1.0.0,>=0.13.2
Requires-Dist: glasbey<1.0.0,>=0.2.1
Requires-Dist: matplotlib<4.0.0,>=3.10.1
Requires-Dist: ipywidgets<9.0.0,>=8.1.7
Requires-Dist: ipykernel<7.0.0,>=6.29.5
Requires-Dist: jupyter<2.0.0,>=1.1.1
Requires-Dist: gseapy<4.0.0,>=1.1.8
Requires-Dist: mygene<4.0.0,>=3.2.2
Provides-Extra: docs
Requires-Dist: sphinx>=8.2; extra == "docs"
Requires-Dist: sphinx-rtd-theme>=1.0; extra == "docs"
Requires-Dist: myst-parser>=0.21; extra == "docs"
Requires-Dist: jupyter-sphinx>=0.3; extra == "docs"
Dynamic: license-file
